gdb/FrameDecorator.py
gdb/FrameIterator.py
gdb/__init__.py
gdb/disassembler.py
gdb/frames.py
gdb/missing_debug.py
gdb/missing_files.py
gdb/missing_objfile.py
gdb/printing.py
gdb/prompt.py
gdb/ptwrite.py
gdb/styling.py
gdb/types.py
gdb/unwinder.py
gdb/xmethod.py
gdb/command/__init__.py
gdb/command/explore.py
gdb/command/frame_filters.py
gdb/command/missing_files.py
gdb/command/pretty_printers.py
gdb/command/prompt.py
gdb/command/type_printers.py
gdb/command/unwinders.py
gdb/command/xmethods.py
gdb/dap/__init__.py
gdb/dap/breakpoint.py
gdb/dap/bt.py
gdb/dap/completions.py
gdb/dap/disassemble.py
gdb/dap/evaluate.py
gdb/dap/events.py
gdb/dap/frames.py
gdb/dap/globalvars.py
gdb/dap/io.py
gdb/dap/launch.py
gdb/dap/locations.py
gdb/dap/memory.py
gdb/dap/modules.py
gdb/dap/next.py
gdb/dap/pause.py
gdb/dap/scopes.py
gdb/dap/server.py
gdb/dap/sources.py
gdb/dap/startup.py
gdb/dap/state.py
gdb/dap/threads.py
gdb/dap/typecheck.py
gdb/dap/varref.py
gdb/function/__init__.py
gdb/function/as_string.py
gdb/function/caller_is.py
gdb/function/strfns.py
gdb/printer/__init__.py
gdb_for_pwndbg/__init__.py
gdb_for_pwndbg/gdb.py
gdb_for_pwndbg/gdbserver.py
gdb_for_pwndbg/_vendor/bin/gdb
gdb_for_pwndbg/_vendor/share/gdb/syscalls/aarch64-linux.xml
gdb_for_pwndbg/_vendor/share/gdb/syscalls/amd64-linux.xml
gdb_for_pwndbg/_vendor/share/gdb/syscalls/arm-linux.xml
gdb_for_pwndbg/_vendor/share/gdb/syscalls/freebsd.xml
gdb_for_pwndbg/_vendor/share/gdb/syscalls/gdb-syscalls.dtd
gdb_for_pwndbg/_vendor/share/gdb/syscalls/i386-linux.xml
gdb_for_pwndbg/_vendor/share/gdb/syscalls/loongarch-linux.xml
gdb_for_pwndbg/_vendor/share/gdb/syscalls/mips-n32-linux.xml
gdb_for_pwndbg/_vendor/share/gdb/syscalls/mips-n64-linux.xml
gdb_for_pwndbg/_vendor/share/gdb/syscalls/mips-o32-linux.xml
gdb_for_pwndbg/_vendor/share/gdb/syscalls/netbsd.xml
gdb_for_pwndbg/_vendor/share/gdb/syscalls/ppc-linux.xml
gdb_for_pwndbg/_vendor/share/gdb/syscalls/ppc64-linux.xml
gdb_for_pwndbg/_vendor/share/gdb/syscalls/s390-linux.xml
gdb_for_pwndbg-17.1.0.post2.dist-info/METADATA
gdb_for_pwndbg-17.1.0.post2.dist-info/WHEEL
gdb_for_pwndbg-17.1.0.post2.dist-info/entry_points.txt
gdb_for_pwndbg-17.1.0.post2.dist-info/top_level.txt
gdb_for_pwndbg-17.1.0.post2.dist-info/RECORD
